datasette_alerts_discord/__init__.py
datasette_alerts_discord-0.1.0a1.dist-info/licenses/LICENSE
datasette_alerts_discord-0.1.0a1.dist-info/METADATA
datasette_alerts_discord-0.1.0a1.dist-info/WHEEL
datasette_alerts_discord-0.1.0a1.dist-info/entry_points.txt
datasette_alerts_discord-0.1.0a1.dist-info/top_level.txt
datasette_alerts_discord-0.1.0a1.dist-info/RECORD
