Metadata-Version: 2.4
Name: datasette-alerts-discord
Version: 0.1.0a1
Author: Alex Garcia
License-Expression: Apache-2.0
Project-URL: Homepage, https://github.com/datasette/datasette-alerts-discord
Project-URL: Changelog, https://github.com/datasette/datasette-alerts-discord/releases
Project-URL: Issues, https://github.com/datasette/datasette-alerts-discord/issues
Project-URL: CI, https://github.com/datasette/datasette-alerts-discord/actions
Classifier: Framework :: Datasette
Requires-Python: >=3.9
License-File: LICENSE
Requires-Dist: datasette>=1a19
Requires-Dist: datasette-alerts
Provides-Extra: test
Requires-Dist: pytest; extra == "test"
Requires-Dist: pytest-asyncio; extra == "test"
Dynamic: license-file
